[{
  "userId": 9,
  "username": "GdWRLeDDp",
  "password": "q7aJMMscI"
}, {
  "userId": 3,
  "username": "28DHAVRYi",
  "password": "eX0FJJccH"
}, {
  "userId": 7,
  "username": "vbiEBQokR",
  "password": "WGcwtBeVI"
}, {
  "userId": 5,
  "username": "QhDdmAave",
  "password": "mViBbdr5o"
}, {
  "userId": 3,
  "username": "fLDB84vqL",
  "password": "hdYCZw01H"
}, {
  "userId": 3,
  "username": "Btqd7wqiJ",
  "password": "KLsVbqOcd"
}, {
  "userId": 8,
  "username": "c9MQJyNE5",
  "password": "dvq4Zpjdw"
}, {
  "userId": 1,
  "username": "FusHZIi0N",
  "password": "cfHZ0dOpu"
}, {
  "userId": 7,
  "username": "mmNwVZI8E",
  "password": "ckI3yYwg8"
}, {
  "userId": 10,
  "username": "OyB64EOut",
  "password": "JhcHrOlmU"
}]